hdl/alu.sv
// alu.sv — pipelined alu + fpu
// int ops : 1-cycle latency (alu_int)
// fp ops  : 3-cycle latency (fpu_addsub / fpu_mul / fpu_div)

module alu (
    input         clk,
    input         reset,
    input         valid_in,
    input  [63:0] a,
    input  [63:0] b,
    input  [4:0]  op,
    input  [5:0]  rob_tag_in,
    output reg        valid_out,
    output reg [63:0] result,
    output reg [5:0]  rob_tag_out
);
    // op codes
    localparam ADD   = 5'd0,  SUB   = 5'd1,  MUL  = 5'd2,  DIV  = 5'd3;
    localparam AND   = 5'd4,  OR    = 5'd5,  XOR  = 5'd6,  NOT  = 5'd7;
    localparam SHR   = 5'd8,  SHL   = 5'd9;
    localparam CMPNZ = 5'd14, CMPGT = 5'd15;

    reg [63:0] comb;
    always @(*) begin
        case (op)
            ADD:   comb = a + b;
            SUB:   comb = a - b;
            MUL:   comb = a * b;
            DIV:   comb = (b == 0) ? 64'd0 : $signed(a) / $signed(b);
            AND:   comb = a & b;
            OR:    comb = a | b;
            XOR:   comb = a ^ b;
            NOT:   comb = ~a;
            SHR:   comb = a >> b[5:0];
            SHL:   comb = a << b[5:0];
            CMPNZ: comb = (a != 0) ? 64'd1 : 64'd0;
            CMPGT: comb = ($signed(a) > $signed(b)) ? 64'd1 : 64'd0;
            default: comb = 64'd0;
        endcase
    end

    // register output — 1 cycle latency
    always @(posedge clk) begin
        if (reset) begin
            valid_out <= 0; result <= 0; rob_tag_out <= 0;
        end else begin
            valid_out   <= valid_in;
            result      <= comb;
            rob_tag_out <= rob_tag_in;
        end
    end
endmodule

test/alu_tb.sv
// tb_alu.v — unit tests for the alu module
module tb_alu;

  reg [63:0] a, b;
  reg  [ 4:0] op;
  wire [63:0] result;

  alu dut (
      .a(a),
      .b(b),
      .op(op),
      .result(result)
  );

  integer pass_count, fail_count;

  task check;
    input [63:0] expected;
    input [255:0] name;
    begin
      if (result === expected) begin
        $display("  pass [%s]: got 0x%016h", name, result);
        pass_count = pass_count + 1;
      end else begin
        $display("  FAIL [%s]: got 0x%016h  expected 0x%016h", name, result, expected);
        fail_count = fail_count + 1;
      end
    end
  endtask

  initial begin
    $dumpfile("sim/tb_alu.vcd");
    $dumpvars(0, tb_alu);
    pass_count = 0;
    fail_count = 0;

    $display("\n--- int ops ---");
    op = 5'd0;
    a  = 64'd20;
    b  = 64'd30;
    #1;
    check(64'd50, "add");
    op = 5'd1;
    a  = 64'd100;
    b  = 64'd40;
    #1;
    check(64'd60, "sub");
    op = 5'd1;
    a  = 64'd5;
    b  = 64'd10;
    #1;
    check(64'hFFFFFFFFFFFFFFFB, "sub_wrap");
    op = 5'd2;
    a  = 64'd6;
    b  = 64'd7;
    #1;
    check(64'd42, "mul");
    op = 5'd2;
    a  = 64'd99;
    b  = 64'd0;
    #1;
    check(64'd0, "mul_zero");
    op = 5'd3;
    a  = 64'd100;
    b  = 64'd4;
    #1;
    check(64'd25, "div");
    op = 5'd3;
    a  = 64'd7;
    b  = 64'd0;
    #1;
    check(64'd0, "div_zero");

    $display("\n--- bitwise ---");
    op = 5'd4;
    a  = 64'hF0;
    b  = 64'hFF;
    #1;
    check(64'hF0, "and");
    op = 5'd4;
    a  = 64'hFF;
    b  = 64'd0;
    #1;
    check(64'd0, "and_zero");
    op = 5'd5;
    a  = 64'hF0;
    b  = 64'h0F;
    #1;
    check(64'hFF, "or");
    op = 5'd6;
    a  = 64'hFF;
    b  = 64'h0F;
    #1;
    check(64'hF0, "xor");
    op = 5'd7;
    a  = 64'd0;
    b  = 64'd0;
    #1;
    check(64'hFFFFFFFFFFFFFFFF, "not");

    $display("\n--- shifts ---");
    op = 5'd8;
    a  = 64'h80;
    b  = 64'd3;
    #1;
    check(64'h10, "shftr");
    op = 5'd9;
    a  = 64'd1;
    b  = 64'd8;
    #1;
    check(64'd256, "shftl");
    op = 5'd8;
    a  = 64'd42;
    b  = 64'd0;
    #1;
    check(64'd42, "shftr_0");

    $display("\n--- fadd ---");
    op = 5'd10;
    a  = 64'h3FF0000000000000;
    b  = 64'h4000000000000000;
    #1;
    check(64'h4008000000000000, "1+2=3");
    a = 64'h3FF0000000000000;
    b = 64'hBFF0000000000000;
    #1;
    check(64'h0000000000000000, "1+(-1)=0");
    a = 64'h7FF0000000000000;
    b = 64'h7FF0000000000000;
    #1;
    check(64'h7FF0000000000000, "inf+inf");
    a = 64'h7FF0000000000000;
    b = 64'hFFF0000000000000;
    #1;
    check(64'h7FF8000000000000, "inf-inf=nan");
    a = 64'h7FF8000000000000;
    b = 64'h3FF0000000000000;
    #1;
    check(64'h7FF8000000000000, "nan+1=nan");
    a = 64'h8000000000000000;
    b = 64'h8000000000000000;
    #1;
    check(64'h8000000000000000, "-0+-0=-0");

    $display("\n--- fsub ---");
    op = 5'd11;
    a  = 64'h4008000000000000;
    b  = 64'h3FF0000000000000;
    #1;
    check(64'h4000000000000000, "3-1=2");
    a = 64'h3FF0000000000000;
    b = 64'h4000000000000000;
    #1;
    check(64'hBFF0000000000000, "1-2=-1");
    a = 64'h4000000000000000;
    b = 64'h0000000000000000;
    #1;
    check(64'h4000000000000000, "x-0=x");
    a = 64'h7FF0000000000000;
    b = 64'h7FF0000000000000;
    #1;
    check(64'h7FF8000000000000, "inf-inf=nan");
    a = 64'h7FF8000000000001;
    b = 64'h3FF0000000000000;
    #1;
    check(64'h7FF8000000000001, "nan-1=nan");

    $display("\n--- fmul ---");
    op = 5'd12;
    a  = 64'h4000000000000000;
    b  = 64'h4008000000000000;
    #1;
    check(64'h4018000000000000, "2*3=6");
    a = 64'hBFF0000000000000;
    b = 64'h4000000000000000;
    #1;
    check(64'hC000000000000000, "-1*2=-2");
    a = 64'h7FF0000000000000;
    b = 64'h0000000000000000;
    #1;
    check(64'h7FF8000000000000, "inf*0=nan");
    a = 64'h7FF0000000000000;
    b = 64'h4000000000000000;
    #1;
    check(64'h7FF0000000000000, "inf*2=inf");
    a = 64'hFFF0000000000000;
    b = 64'h4000000000000000;
    #1;
    check(64'hFFF0000000000000, "-inf*2=-inf");
    a = 64'h8000000000000000;
    b = 64'h4000000000000000;
    #1;
    check(64'h8000000000000000, "-0*2=-0");
    a = 64'h0010000000000000;
    b = 64'h4000000000000000;
    #1;
    check(64'h0020000000000000, "subn*2");
    a = 64'h7FF8000000000000;
    b = 64'h4000000000000000;
    #1;
    check(64'h7FF8000000000000, "nan*2=nan");
    a = 64'h3FD5555555555555;
    b = 64'h4008000000000000;
    #1;
    check(64'h3FF0000000000000, "fmul_round");

    $display("\n--- fdiv ---");
    op = 5'd13;
    a  = 64'h3FF0000000000000;
    b  = 64'h4000000000000000;
    #1;
    check(64'h3FE0000000000000, "1/2=0.5");
    a = 64'h4000000000000000;
    b = 64'h3FF0000000000000;
    #1;
    check(64'h4000000000000000, "2/1=2");
    a = 64'h4018000000000000;
    b = 64'h4000000000000000;
    #1;
    check(64'h4008000000000000, "6/2=3");
    a = 64'h3FF0000000000000;
    b = 64'h4008000000000000;
    #1;
    check(64'h3FD5555555555555, "1/3_round");
    a = 64'h7FF0000000000000;
    b = 64'h7FF0000000000000;
    #1;
    check(64'h7FF8000000000000, "inf/inf=nan");
    a = 64'h0000000000000000;
    b = 64'h0000000000000000;
    #1;
    check(64'h7FF8000000000000, "0/0=nan");
    a = 64'h3FF0000000000000;
    b = 64'h0000000000000000;
    #1;
    check(64'h7FF0000000000000, "1/0=inf");
    a = 64'h0000000000000000;
    b = 64'h3FF0000000000000;
    #1;
    check(64'h0000000000000000, "0/1=0");
    a = 64'h7FF0000000000000;
    b = 64'h4000000000000000;
    #1;
    check(64'h7FF0000000000000, "inf/2=inf");
    a = 64'h4000000000000000;
    b = 64'h7FF0000000000000;
    #1;
    check(64'h0000000000000000, "2/inf=0");
    a = 64'h7FF8000000000000;
    b = 64'h3FF0000000000000;
    #1;
    check(64'h7FF8000000000000, "nan/1=nan");
    a = 64'h3FF0000000000000;
    b = 64'h7FF8000000000000;
    #1;
    check(64'h7FF8000000000000, "1/nan=nan");
    a = 64'h0010000000000000;
    b = 64'h4000000000000000;
    #1;
    check(64'h0008000000000000, "norm/2=subn");
    a = 64'h0000000000000001;
    b = 64'h3FF0000000000000;
    #1;
    check(64'h0000000000000001, "tiny/1=tiny");
    a = 64'hBFF0000000000000;
    b = 64'h4000000000000000;
    #1;
    check(64'hBFE0000000000000, "-1/2=-0.5");

    $display("\n--- results: %0d passed, %0d failed ---", pass_count, fail_count);
    $finish;
  end
endmodule

sim/tb_alu.vcd
$date
	Sun Apr 12 14:04:34 2026
$end
$version
	Icarus Verilog
$end
$timescale
	1s
$end
$scope module tb_alu $end
$var wire 64 ! result [63:0] $end
$var reg 64 " a [63:0] $end
$var reg 64 # b [63:0] $end
$var reg 5 $ op [4:0] $end
$var integer 32 % fail_count [31:0] $end
$var integer 32 & pass_count [31:0] $end
$scope module dut $end
$var wire 64 ' a [63:0] $end
$var wire 64 ( b [63:0] $end
$var wire 5 ) op [4:0] $end
$var reg 64 * result [63:0] $end
$scope function fp_add $end
$scope begin norm_loop $end
$upscope $end
$upscope $end
$scope function fp_div $end
$upscope $end
$scope function fp_mul $end
$upscope $end
$upscope $end
$scope task check $end
$var reg 64 + expected [63:0] $end
$var reg 256 , name [255:0] $end
$upscope $end
$upscope $end
$enddefinitions $end
$comment Show the parameter values. $end
$dumpall
$end
#0
$dumpvars
bx ,
bx +
b110010 *
b0 )
b11110 (
b10100 '
b0 &
b0 %
b0 $
b11110 #
b10100 "
b110010 !
$end
#1
b111100 !
b111100 *
b101000 #
b101000 (
b1100100 "
b1100100 '
b1 $
b1 )
b1 &
b11000010110010001100100 ,
b110010 +
#2
b1111111111111111111111111111111111111111111111111111111111111011 !
b1111111111111111111111111111111111111111111111111111111111111011 *
b1010 #
b1010 (
b101 "
b101 '
b10 &
b11100110111010101100010 ,
b111100 +
#3
b101010 !
b101010 *
b111 #
b111 (
b110 "
b110 '
b10 $
b10 )
b11 &
b111001101110101011000100101111101110111011100100110000101110000 ,
b1111111111111111111111111111111111111111111111111111111111111011 +
#4
b0 !
b0 *
b0 #
b0 (
b1100011 "
b1100011 '
b100 &
b11011010111010101101100 ,
b101010 +
#5
b11001 !
b11001 *
b100 #
b100 (
b1100100 "
b1100100 '
b11 $
b11 )
b101 &
b110110101110101011011000101111101111010011001010111001001101111 ,
b0 +
#6
b0 !
b0 *
b0 #
b0 (
b111 "
b111 '
b110 &
b11001000110100101110110 ,
b11001 +
#7
b11110000 !
b11110000 *
b11111111 #
b11111111 (
b11110000 "
b11110000 '
b100 $
b100 )
b111 &
b110010001101001011101100101111101111010011001010111001001101111 ,
b0 +
#8
b0 !
b0 *
b0 #
b0 (
b11111111 "
b11111111 '
b1000 &
b11000010110111001100100 ,
b11110000 +
#9
b11111111 !
b11111111 *
b1111 #
b1111 (
b11110000 "
b11110000 '
b101 $
b101 )
b1001 &
b110000101101110011001000101111101111010011001010111001001101111 ,
b0 +
#10
b11110000 !
b11110000 *
b11111111 "
b11111111 '
b110 $
b110 )
b1010 &
b110111101110010 ,
b11111111 +
#11
b1111111111111111111111111111111111111111111111111111111111111111 !
b1111111111111111111111111111111111111111111111111111111111111111 *
b0 #
b0 (
b0 "
b0 '
b111 $
b111 )
b1011 &
b11110000110111101110010 ,
b11110000 +
#12
b10000 !
b10000 *
b11 #
b11 (
b10000000 "
b10000000 '
b1000 $
b1000 )
b1100 &
b11011100110111101110100 ,
b1111111111111111111111111111111111111111111111111111111111111111 +
#13
b100000000 !
b100000000 *
b1000 #
b1000 (
b1 "
b1 '
b1001 $
b1001 )
b1101 &
b111001101101000011001100111010001110010 ,
b10000 +
#14
b101010 !
b101010 *
b0 #
b0 (
b101010 "
b101010 '
b1000 $
b1000 )
b1110 &
b111001101101000011001100111010001101100 ,
b100000000 +
#15
b100000000001000000000000000000000000000000000000000000000000000 !
b100000000001000000000000000000000000000000000000000000000000000 *
b100000000000000000000000000000000000000000000000000000000000000 #
b100000000000000000000000000000000000000000000000000000000000000 (
b11111111110000000000000000000000000000000000000000000000000000 "
b11111111110000000000000000000000000000000000000000000000000000 '
b1010 $
b1010 )
b1111 &
b1110011011010000110011001110100011100100101111100110000 ,
b101010 +
#16
b0 !
b0 *
b1011111111110000000000000000000000000000000000000000000000000000 #
b1011111111110000000000000000000000000000000000000000000000000000 (
b10000 &
b11000100101011001100100011110100110011 ,
b100000000001000000000000000000000000000000000000000000000000000 +
#17
b111111111110000000000000000000000000000000000000000000000000000 !
b111111111110000000000000000000000000000000000000000000000000000 *
b111111111110000000000000000000000000000000000000000000000000000 #
b111111111110000000000000000000000000000000000000000000000000000 (
b111111111110000000000000000000000000000000000000000000000000000 "
b111111111110000000000000000000000000000000000000000000000000000 '
b10001 &
b11000100101011001010000010110100110001001010010011110100110000 ,
b0 +
#18
b111111111111000000000000000000000000000000000000000000000000000 !
b111111111111000000000000000000000000000000000000000000000000000 *
b1111111111110000000000000000000000000000000000000000000000000000 #
b1111111111110000000000000000000000000000000000000000000000000000 (
b10010 &
b1101001011011100110011000101011011010010110111001100110 ,
b111111111110000000000000000000000000000000000000000000000000000 +
#19
b11111111110000000000000000000000000000000000000000000000000000 #
b11111111110000000000000000000000000000000000000000000000000000 (
b111111111111000000000000000000000000000000000000000000000000000 "
b111111111111000000000000000000000000000000000000000000000000000 '
b10011 &
b110100101101110011001100010110101101001011011100110011000111101011011100110000101101110 ,
b111111111111000000000000000000000000000000000000000000000000000 +
#20
b1000000000000000000000000000000000000000000000000000000000000000 !
b1000000000000000000000000000000000000000000000000000000000000000 *
b1000000000000000000000000000000000000000000000000000000000000000 #
b1000000000000000000000000000000000000000000000000000000000000000 (
b1000000000000000000000000000000000000000000000000000000000000000 "
b1000000000000000000000000000000000000000000000000000000000000000 '
b10100 &
b11011100110000101101110001010110011000100111101011011100110000101101110 ,
#21
b100000000000000000000000000000000000000000000000000000000000000 !
b100000000000000000000000000000000000000000000000000000000000000 *
b11111111110000000000000000000000000000000000000000000000000000 #
b11111111110000000000000000000000000000000000000000000000000000 (
b100000000001000000000000000000000000000000000000000000000000000 "
b100000000001000000000000000000000000000000000000000000000000000 '
b1011 $
b1011 )
b10101 &
b10110100110000001010110010110100110000001111010010110100110000 ,
b1000000000000000000000000000000000000000000000000000000000000000 +
#22
b1011111111110000000000000000000000000000000000000000000000000000 !
b1011111111110000000000000000000000000000000000000000000000000000 *
b100000000000000000000000000000000000000000000000000000000000000 #
b100000000000000000000000000000000000000000000000000000000000000 (
b11111111110000000000000000000000000000000000000000000000000000 "
b11111111110000000000000000000000000000000000000000000000000000 '
b10110 &
b11001100101101001100010011110100110010 ,
b100000000000000000000000000000000000000000000000000000000000000 +
#23
b100000000000000000000000000000000000000000000000000000000000000 !
b100000000000000000000000000000000000000000000000000000000000000 *
b0 #
b0 (
b100000000000000000000000000000000000000000000000000000000000000 "
b100000000000000000000000000000000000000000000000000000000000000 '
b10111 &
b1100010010110100110010001111010010110100110001 ,
b1011111111110000000000000000000000000000000000000000000000000000 +
#24
b111111111111000000000000000000000000000000000000000000000000000 !
b111111111111000000000000000000000000000000000000000000000000000 *
b111111111110000000000000000000000000000000000000000000000000000 #
b111111111110000000000000000000000000000000000000000000000000000 (
b111111111110000000000000000000000000000000000000000000000000000 "
b111111111110000000000000000000000000000000000000000000000000000 '
b11000 &
b111100000101101001100000011110101111000 ,
b100000000000000000000000000000000000000000000000000000000000000 +
#25
b111111111111000000000000000000000000000000000000000000000000001 !
b111111111111000000000000000000000000000000000000000000000000001 *
b11111111110000000000000000000000000000000000000000000000000000 #
b11111111110000000000000000000000000000000000000000000000000000 (
b111111111111000000000000000000000000000000000000000000000000001 "
b111111111111000000000000000000000000000000000000000000000000001 '
b11001 &
b110100101101110011001100010110101101001011011100110011000111101011011100110000101101110 ,
b111111111111000000000000000000000000000000000000000000000000000 +
#26
b100000000011000000000000000000000000000000000000000000000000000 !
b100000000011000000000000000000000000000000000000000000000000000 *
b100000000001000000000000000000000000000000000000000000000000000 #
b100000000001000000000000000000000000000000000000000000000000000 (
b100000000000000000000000000000000000000000000000000000000000000 "
b100000000000000000000000000000000000000000000000000000000000000 '
b1100 $
b1100 )
b11010 &
b11011100110000101101110001011010011000100111101011011100110000101101110 ,
b111111111111000000000000000000000000000000000000000000000000001 +
#27
b1100000000000000000000000000000000000000000000000000000000000000 !
b1100000000000000000000000000000000000000000000000000000000000000 *
b100000000000000000000000000000000000000000000000000000000000000 #
b100000000000000000000000000000000000000000000000000000000000000 (
b1011111111110000000000000000000000000000000000000000000000000000 "
b1011111111110000000000000000000000000000000000000000000000000000 '
b11011 &
b11001000101010001100110011110100110110 ,
b100000000011000000000000000000000000000000000000000000000000000 +
#28
b111111111111000000000000000000000000000000000000000000000000000 !
b111111111111000000000000000000000000000000000000000000000000000 *
b0 #
b0 (
b111111111110000000000000000000000000000000000000000000000000000 "
b111111111110000000000000000000000000000000000000000000000000000 '
b11100 &
b101101001100010010101000110010001111010010110100110010 ,
b1100000000000000000000000000000000000000000000000000000000000000 +
#29
b111111111110000000000000000000000000000000000000000000000000000 !
b111111111110000000000000000000000000000000000000000000000000000 *
b100000000000000000000000000000000000000000000000000000000000000 #
b100000000000000000000000000000000000000000000000000000000000000 (
b11101 &
b11010010110111001100110001010100011000000111101011011100110000101101110 ,
b111111111111000000000000000000000000000000000000000000000000000 +
#30
b1111111111110000000000000000000000000000000000000000000000000000 !
b1111111111110000000000000000000000000000000000000000000000000000 *
b1111111111110000000000000000000000000000000000000000000000000000 "
b1111111111110000000000000000000000000000000000000000000000000000 '
b11110 &
b11010010110111001100110001010100011001000111101011010010110111001100110 ,
b111111111110000000000000000000000000000000000000000000000000000 +
#31
b1000000000000000000000000000000000000000000000000000000000000000 !
b1000000000000000000000000000000000000000000000000000000000000000 *
b1000000000000000000000000000000000000000000000000000000000000000 "
b1000000000000000000000000000000000000000000000000000000000000000 '
b11111 &
b10110101101001011011100110011000101010001100100011110100101101011010010110111001100110 ,
b1111111111110000000000000000000000000000000000000000000000000000 +
#32
b100000000000000000000000000000000000000000000000000000 !
b100000000000000000000000000000000000000000000000000000 *
b10000000000000000000000000000000000000000000000000000 "
b10000000000000000000000000000000000000000000000000000 '
b100000 &
b101101001100000010101000110010001111010010110100110000 ,
b1000000000000000000000000000000000000000000000000000000000000000 +
#33
b111111111111000000000000000000000000000000000000000000000000000 !
b111111111111000000000000000000000000000000000000000000000000000 *
b111111111111000000000000000000000000000000000000000000000000000 "
b111111111111000000000000000000000000000000000000000000000000000 '
b100001 &
b11100110111010101100010011011100010101000110010 ,
b100000000000000000000000000000000000000000000000000000 +
#34
b11111111110000000000000000000000000000000000000000000000000000 !
b11111111110000000000000000000000000000000000000000000000000000 *
b100000000001000000000000000000000000000000000000000000000000000 #
b100000000001000000000000000000000000000000000000000000000000000 (
b11111111010101010101010101010101010101010101010101010101010101 "
b11111111010101010101010101010101010101010101010101010101010101 '
b100010 &
b11011100110000101101110001010100011001000111101011011100110000101101110 ,
b111111111111000000000000000000000000000000000000000000000000000 +
#35
b11111111100000000000000000000000000000000000000000000000000000 !
b11111111100000000000000000000000000000000000000000000000000000 *
b100000000000000000000000000000000000000000000000000000000000000 #
b100000000000000000000000000000000000000000000000000000000000000 (
b11111111110000000000000000000000000000000000000000000000000000 "
b11111111110000000000000000000000000000000000000000000000000000 '
b1101 $
b1101 )
b100011 &
b1100110011011010111010101101100010111110111001001101111011101010110111001100100 ,
b11111111110000000000000000000000000000000000000000000000000000 +
#36
b100000000000000000000000000000000000000000000000000000000000000 !
b100000000000000000000000000000000000000000000000000000000000000 *
b11111111110000000000000000000000000000000000000000000000000000 #
b11111111110000000000000000000000000000000000000000000000000000 (
b100000000000000000000000000000000000000000000000000000000000000 "
b100000000000000000000000000000000000000000000000000000000000000 '
b100100 &
b110001001011110011001000111101001100000010111000110101 ,
b11111111100000000000000000000000000000000000000000000000000000 +
#37
b100000000001000000000000000000000000000000000000000000000000000 !
b100000000001000000000000000000000000000000000000000000000000000 *
b100000000000000000000000000000000000000000000000000000000000000 #
b100000000000000000000000000000000000000000000000000000000000000 (
b100000000011000000000000000000000000000000000000000000000000000 "
b100000000011000000000000000000000000000000000000000000000000000 '
b100101 &
b11001000101111001100010011110100110010 ,
b100000000000000000000000000000000000000000000000000000000000000 +
#38
b11111111010101010101010101010101010101010101010101010101010101 !
b11111111010101010101010101010101010101010101010101010101010101 *
b100000000001000000000000000000000000000000000000000000000000000 #
b100000000001000000000000000000000000000000000000000000000000000 (
b11111111110000000000000000000000000000000000000000000000000000 "
b11111111110000000000000000000000000000000000000000000000000000 '
b100110 &
b11011000101111001100100011110100110011 ,
b100000000001000000000000000000000000000000000000000000000000000 +
#39
b111111111111000000000000000000000000000000000000000000000000000 !
b111111111111000000000000000000000000000000000000000000000000000 *
b111111111110000000000000000000000000000000000000000000000000000 #
b111111111110000000000000000000000000000000000000000000000000000 (
b111111111110000000000000000000000000000000000000000000000000000 "
b111111111110000000000000000000000000000000000000000000000000000 '
b100111 &
b1100010010111100110011010111110111001001101111011101010110111001100100 ,
b11111111010101010101010101010101010101010101010101010101010101 +
#40
b0 #
b0 (
b0 "
b0 '
b101000 &
b110100101101110011001100010111101101001011011100110011000111101011011100110000101101110 ,
b111111111111000000000000000000000000000000000000000000000000000 +
#41
b111111111110000000000000000000000000000000000000000000000000000 !
b111111111110000000000000000000000000000000000000000000000000000 *
b11111111110000000000000000000000000000000000000000000000000000 "
b11111111110000000000000000000000000000000000000000000000000000 '
b101001 &
b110000001011110011000000111101011011100110000101101110 ,
#42
b0 !
b0 *
b11111111110000000000000000000000000000000000000000000000000000 #
b11111111110000000000000000000000000000000000000000000000000000 (
b0 "
b0 '
b101010 &
b110001001011110011000000111101011010010110111001100110 ,
b111111111110000000000000000000000000000000000000000000000000000 +
#43
b111111111110000000000000000000000000000000000000000000000000000 !
b111111111110000000000000000000000000000000000000000000000000000 *
b100000000000000000000000000000000000000000000000000000000000000 #
b100000000000000000000000000000000000000000000000000000000000000 (
b111111111110000000000000000000000000000000000000000000000000000 "
b111111111110000000000000000000000000000000000000000000000000000 '
b101011 &
b11000000101111001100010011110100110000 ,
b0 +
#44
b0 !
b0 *
b111111111110000000000000000000000000000000000000000000000000000 #
b111111111110000000000000000000000000000000000000000000000000000 (
b100000000000000000000000000000000000000000000000000000000000000 "
b100000000000000000000000000000000000000000000000000000000000000 '
b101100 &
b11010010110111001100110001011110011001000111101011010010110111001100110 ,
b111111111110000000000000000000000000000000000000000000000000000 +
#45
b111111111111000000000000000000000000000000000000000000000000000 !
b111111111111000000000000000000000000000000000000000000000000000 *
b11111111110000000000000000000000000000000000000000000000000000 #
b11111111110000000000000000000000000000000000000000000000000000 (
b111111111111000000000000000000000000000000000000000000000000000 "
b111111111111000000000000000000000000000000000000000000000000000 '
b101101 &
b110010001011110110100101101110011001100011110100110000 ,
b0 +
#46
b111111111111000000000000000000000000000000000000000000000000000 #
b111111111111000000000000000000000000000000000000000000000000000 (
b11111111110000000000000000000000000000000000000000000000000000 "
b11111111110000000000000000000000000000000000000000000000000000 '
b101110 &
b11011100110000101101110001011110011000100111101011011100110000101101110 ,
b111111111111000000000000000000000000000000000000000000000000000 +
#47
b1000000000000000000000000000000000000000000000000000 !
b1000000000000000000000000000000000000000000000000000 *
b100000000000000000000000000000000000000000000000000000000000000 #
b100000000000000000000000000000000000000000000000000000000000000 (
b10000000000000000000000000000000000000000000000000000 "
b10000000000000000000000000000000000000000000000000000 '
b101111 &
b1100010010111101101110011000010110111000111101011011100110000101101110 ,
#48
b1 !
b1 *
b11111111110000000000000000000000000000000000000000000000000000 #
b11111111110000000000000000000000000000000000000000000000000000 (
b1 "
b1 '
b110000 &
b110111001101111011100100110110100101111001100100011110101110011011101010110001001101110 ,
b1000000000000000000000000000000000000000000000000000 +
#49
b1011111111100000000000000000000000000000000000000000000000000000 !
b1011111111100000000000000000000000000000000000000000000000000000 *
b100000000000000000000000000000000000000000000000000000000000000 #
b100000000000000000000000000000000000000000000000000000000000000 (
b1011111111110000000000000000000000000000000000000000000000000000 "
b1011111111110000000000000000000000000000000000000000000000000000 '
b110001 &
b111010001101001011011100111100100101111001100010011110101110100011010010110111001111001 ,
b1 +
#50
b110010 &
b1011010011000100101111001100100011110100101101001100000010111000110101 ,
b1011111111100000000000000000000000000000000000000000000000000000 +
