hdl/mem_module.sv
// memory module
// has two ports: one for instr fetch and one for data load/store
module mem_module #(
    parameter MEM_SIZE = 512 * 1024
) (
    input clk,
    input [63:0] fetch_addr,
    output [31:0] instr_out,
    input [63:0] data_addr,
    input [63:0] write_data,
    input we,
    output [63:0] read_data
);

  // actual mem
  reg [7:0] bytes[0:MEM_SIZE-1];

  // instr fetch port
  assign instr_out = {
    bytes[fetch_addr+3], bytes[fetch_addr+2], bytes[fetch_addr+1], bytes[fetch_addr]
  };
  assign read_data = {
    bytes[data_addr+7],
    bytes[data_addr+6],
    bytes[data_addr+5],
    bytes[data_addr+4],
    bytes[data_addr+3],
    bytes[data_addr+2],
    bytes[data_addr+1],
    bytes[data_addr]
  };

  // load/store port
  always @(posedge clk) begin
    if (we) begin
      bytes[data_addr]   <= write_data[7:0];
      bytes[data_addr+1] <= write_data[15:8];
      bytes[data_addr+2] <= write_data[23:16];
      bytes[data_addr+3] <= write_data[31:24];
      bytes[data_addr+4] <= write_data[39:32];
      bytes[data_addr+5] <= write_data[47:40];
      bytes[data_addr+6] <= write_data[55:48];
      bytes[data_addr+7] <= write_data[63:56];
    end
  end
endmodule

test/mem_tb.sv
// tb_mem.v — unit tests for mem_module
module tb_mem;

  reg clk;
  reg [63:0] fetch_addr, data_addr, write_data;
  reg         we;
  wire [31:0] instr_out;
  wire [63:0] read_data;

  mem_module dut (
      .clk       (clk),
      .fetch_addr(fetch_addr),
      .instr_out (instr_out),
      .data_addr (data_addr),
      .write_data(write_data),
      .we        (we),
      .read_data (read_data)
  );

  always #5 clk = ~clk;

  integer pass_count, fail_count;

  task check64;
    input [63:0] expected, got;
    input [255:0] name;
    begin
      if (got === expected) begin
        $display("  pass [%s]: 0x%016h", name, got);
        pass_count = pass_count + 1;
      end else begin
        $display("  FAIL [%s]: got 0x%016h  exp 0x%016h", name, got, expected);
        fail_count = fail_count + 1;
      end
    end
  endtask

  task check32;
    input [31:0] expected, got;
    input [255:0] name;
    begin
      if (got === expected) begin
        $display("  pass [%s]: 0x%08h", name, got);
        pass_count = pass_count + 1;
      end else begin
        $display("  FAIL [%s]: got 0x%08h  exp 0x%08h", name, got, expected);
        fail_count = fail_count + 1;
      end
    end
  endtask

  task mem_write64;
    input [63:0] addr, val;
    begin
      we = 1;
      data_addr = addr;
      write_data = val;
      @(posedge clk);
      #1;
      we = 0;
    end
  endtask

  task mem_read64;
    input [63:0] addr;
    begin
      we = 0;
      data_addr = addr;
      @(posedge clk);
      #1;
    end
  endtask

  initial begin
    $dumpfile("sim/tb_mem.vcd");
    $dumpvars(0, tb_mem);
    clk = 0;
    pass_count = 0;
    fail_count = 0;
    we = 0;
    fetch_addr = 0;
    data_addr = 0;
    write_data = 0;
    @(posedge clk);
    @(posedge clk);

    // basic store/load via data port
    $display("\n--- basic r/w ---");
    mem_write64(64'h100, 64'hDEADBEEFCAFEBABE);
    mem_read64(64'h100);
    check64(64'hDEADBEEFCAFEBABE, read_data, "rw_0x100");

    mem_write64(64'h108, 64'd42);
    mem_read64(64'h108);
    check64(64'd42, read_data, "rw_0x108");

    // adjacent addrs don't alias
    mem_write64(64'h200, 64'd11);
    mem_write64(64'h208, 64'd99);
    mem_read64(64'h200);
    check64(64'd11, read_data, "no_alias_lo");
    mem_read64(64'h208);
    check64(64'd99, read_data, "no_alias_hi");

    // overwrite
    $display("\n--- overwrite ---");
    mem_write64(64'h300, 64'd1);
    mem_write64(64'h300, 64'd2);
    mem_read64(64'h300);
    check64(64'd2, read_data, "overwrite");

    // edge values
    $display("\n--- edge values ---");
    mem_write64(64'h400, 64'd0);
    mem_read64(64'h400);
    check64(64'd0, read_data, "zero_val");

    mem_write64(64'h500, 64'hFFFFFFFFFFFFFFFF);
    mem_read64(64'h500);
    check64(64'hFFFFFFFFFFFFFFFF, read_data, "all_ones");

    // fp bit pattern round-trips
    $display("\n--- fp bit patterns ---");
    mem_write64(64'h600, 64'h3FF0000000000000);
    mem_read64(64'h600);
    check64(64'h3FF0000000000000, read_data, "fp_1.0");

    mem_write64(64'h608, 64'h7FF0000000000000);
    mem_read64(64'h608);
    check64(64'h7FF0000000000000, read_data, "fp_inf");

    mem_write64(64'h610, 64'h7FF8000000000000);
    mem_read64(64'h610);
    check64(64'h7FF8000000000000, read_data, "fp_nan");

    // fetch port: little-endian 32-bit instr read
    $display("\n--- fetch port ---");
    dut.bytes[64'h2000] = 8'hAB;
    dut.bytes[64'h2001] = 8'hCD;
    dut.bytes[64'h2002] = 8'hEF;
    dut.bytes[64'h2003] = 8'h01;
    fetch_addr = 64'h2000;
    @(posedge clk);
    #1;
    check32(32'h01EFCDAB, instr_out, "instr_le");

    $display("\n--- results: %0d passed, %0d failed ---", pass_count, fail_count);
    $finish;
  end
endmodule

sim/tb_mem.vcd
$date
	Sun Apr 12 14:04:34 2026
$end
$version
	Icarus Verilog
$end
$timescale
	1s
$end
$scope module tb_mem $end
$var wire 64 ! read_data [63:0] $end
$var wire 32 " instr_out [31:0] $end
$var reg 1 # clk $end
$var reg 64 $ data_addr [63:0] $end
$var reg 64 % fetch_addr [63:0] $end
$var reg 1 & we $end
$var reg 64 ' write_data [63:0] $end
$var integer 32 ( fail_count [31:0] $end
$var integer 32 ) pass_count [31:0] $end
$scope module dut $end
$var wire 1 # clk $end
$var wire 64 * data_addr [63:0] $end
$var wire 64 + fetch_addr [63:0] $end
$var wire 1 & we $end
$var wire 64 , write_data [63:0] $end
$var wire 64 - read_data [63:0] $end
$var wire 32 . instr_out [31:0] $end
$var parameter 64 / MEM_SIZE $end
$upscope $end
$scope task check32 $end
$var reg 32 0 expected [31:0] $end
$var reg 32 1 got [31:0] $end
$var reg 256 2 name [255:0] $end
$upscope $end
$scope task check64 $end
$var reg 64 3 expected [63:0] $end
$var reg 64 4 got [63:0] $end
$var reg 256 5 name [255:0] $end
$upscope $end
$scope task mem_read64 $end
$var reg 64 6 addr [63:0] $end
$upscope $end
$scope task mem_write64 $end
$var reg 64 7 addr [63:0] $end
$var reg 64 8 val [63:0] $end
$upscope $end
$upscope $end
$enddefinitions $end
$comment Show the parameter values. $end
$dumpall
b10000000000000000000 /
$end
#0
$dumpvars
bx 8
bx 7
bx 6
bx 5
bx 4
bx 3
bx 2
bx 1
bx 0
bx .
bx -
b0 ,
b0 +
b0 *
b0 )
b0 (
b0 '
0&
b0 %
b0 $
0#
bx "
bx !
$end
#5
1#
#10
0#
#15
b1101111010101101101111101110111111001010111111101011101010111110 '
b1101111010101101101111101110111111001010111111101011101010111110 ,
b100000000 $
b100000000 *
1&
b1101111010101101101111101110111111001010111111101011101010111110 8
b100000000 7
1#
#20
0#
#25
b1101111010101101101111101110111111001010111111101011101010111110 !
b1101111010101101101111101110111111001010111111101011101010111110 -
1#
#26
b100000000 6
0&
#30
0#
#35
1#
#36
b101010 '
b101010 ,
bx !
bx -
b100001000 $
b100001000 *
1&
b101010 8
b100001000 7
b1 )
b111001001110111010111110011000001111000001100010011000000110000 5
b1101111010101101101111101110111111001010111111101011101010111110 4
b1101111010101101101111101110111111001010111111101011101010111110 3
#40
0#
#45
b101010 !
b101010 -
1#
#46
b100001000 6
0&
#50
0#
#55
1#
#56
b1011 '
b1011 ,
bx !
bx -
b1000000000 $
b1000000000 *
1&
b1011 8
b1000000000 7
b10 )
b111001001110111010111110011000001111000001100010011000000111000 5
b101010 4
b101010 3
#60
0#
#65
b1011 !
b1011 -
1#
#66
b1100011 '
b1100011 ,
bx !
bx -
b1000001000 $
b1000001000 *
b1100011 8
b1000001000 7
1&
#70
0#
#75
b1100011 !
b1100011 -
1#
#76
b1011 !
b1011 -
b1000000000 $
b1000000000 *
b1000000000 6
0&
#80
0#
#85
1#
#86
b1100011 !
b1100011 -
b1000001000 $
b1000001000 *
b1000001000 6
b11 )
b110111001101111010111110110000101101100011010010110000101110011010111110110110001101111 5
b1011 4
b1011 3
#90
0#
#95
1#
#96
b1 '
b1 ,
bx !
bx -
b1100000000 $
b1100000000 *
1&
b1 8
b1100000000 7
b100 )
b110111001101111010111110110000101101100011010010110000101110011010111110110100001101001 5
b1100011 4
b1100011 3
#100
0#
#105
b1 !
b1 -
1#
#106
b10 '
b10 ,
b10 8
1&
#110
0#
#115
b10 !
b10 -
1#
#116
b1100000000 6
0&
#120
0#
#125
1#
#126
b0 '
b0 ,
bx !
bx -
b10000000000 $
b10000000000 *
1&
b0 8
b10000000000 7
b101 )
b11011110111011001100101011100100111011101110010011010010111010001100101 5
b10 4
b10 3
#130
0#
#135
b0 !
b0 -
1#
#136
b10000000000 6
0&
#140
0#
#145
1#
#146
b1111111111111111111111111111111111111111111111111111111111111111 '
b1111111111111111111111111111111111111111111111111111111111111111 ,
bx !
bx -
b10100000000 $
b10100000000 *
1&
b1111111111111111111111111111111111111111111111111111111111111111 8
b10100000000 7
b110 )
b111101001100101011100100110111101011111011101100110000101101100 5
b0 4
b0 3
#150
0#
#155
b1111111111111111111111111111111111111111111111111111111111111111 !
b1111111111111111111111111111111111111111111111111111111111111111 -
1#
#156
b10100000000 6
0&
#160
0#
#165
1#
#166
b11111111110000000000000000000000000000000000000000000000000000 '
b11111111110000000000000000000000000000000000000000000000000000 ,
bx !
bx -
b11000000000 $
b11000000000 *
1&
b11111111110000000000000000000000000000000000000000000000000000 8
b11000000000 7
b111 )
b110000101101100011011000101111101101111011011100110010101110011 5
b1111111111111111111111111111111111111111111111111111111111111111 4
b1111111111111111111111111111111111111111111111111111111111111111 3
#170
0#
#175
b11111111110000000000000000000000000000000000000000000000000000 !
b11111111110000000000000000000000000000000000000000000000000000 -
1#
#176
b11000000000 6
0&
#180
0#
#185
1#
#186
b111111111110000000000000000000000000000000000000000000000000000 '
b111111111110000000000000000000000000000000000000000000000000000 ,
bx !
bx -
b11000001000 $
b11000001000 *
1&
b111111111110000000000000000000000000000000000000000000000000000 8
b11000001000 7
b1000 )
b11001100111000001011111001100010010111000110000 5
b11111111110000000000000000000000000000000000000000000000000000 4
b11111111110000000000000000000000000000000000000000000000000000 3
#190
0#
#195
b111111111110000000000000000000000000000000000000000000000000000 !
b111111111110000000000000000000000000000000000000000000000000000 -
1#
#196
b11000001000 6
0&
#200
0#
#205
1#
#206
b111111111111000000000000000000000000000000000000000000000000000 '
b111111111111000000000000000000000000000000000000000000000000000 ,
bx !
bx -
b11000010000 $
b11000010000 *
1&
b111111111111000000000000000000000000000000000000000000000000000 8
b11000010000 7
b1001 )
b11001100111000001011111011010010110111001100110 5
b111111111110000000000000000000000000000000000000000000000000000 4
b111111111110000000000000000000000000000000000000000000000000000 3
#210
0#
#215
b111111111111000000000000000000000000000000000000000000000000000 !
b111111111111000000000000000000000000000000000000000000000000000 -
1#
#216
b11000010000 6
0&
#220
0#
#225
1#
#226
b1111011111100110110101011 "
b1111011111100110110101011 .
b10000000000000 %
b10000000000000 +
b1010 )
b11001100111000001011111011011100110000101101110 5
b111111111111000000000000000000000000000000000000000000000000000 4
b111111111111000000000000000000000000000000000000000000000000000 3
#230
0#
#235
1#
#236
b1011 )
b110100101101110011100110111010001110010010111110110110001100101 2
b1111011111100110110101011 1
b1111011111100110110101011 0
