hdl/reg_file.sv
// regfile.sv — architectural + physical register files
// arch reg file: 32 regs, updated at commit
// phys reg file: 64 regs, written by execution units

// architectural reg file (commit-only writes)
module reg_file (
    input         clk,
    input         reset,
    input  [63:0] data,
    input  [4:0]  raddr1,
    input  [4:0]  raddr2,
    input  [4:0]  raddr3,
    input  [4:0]  waddr,
    input         write,
    output [63:0] r1,
    output [63:0] r2,
    output [63:0] r3
);

    reg [63:0] registers [0:31];

    // async read
    assign r1 = registers[raddr1];
    assign r2 = registers[raddr2];
    assign r3 = registers[raddr3];

    integer i;
    always @(posedge clk) begin
        if (reset) begin
            for (i = 0; i < 31; i = i + 1)
                registers[i] <= 64'd0;
            // r31 = stack ptr init = MEM_SIZE
            registers[31] <= 64'd524288;
        end else if (write && waddr != 5'd0) begin
            registers[waddr] <= data;
        end
    end

endmodule


// physical reg file — 64 entries
// written by functional units via cdb broadcast
// read by reservation stations at issue
module phys_reg_file #(
    parameter NPHYS = 64
) (
    input         clk,
    input         reset,
    // write port (cdb broadcast)
    input                          wr_en,
    input  [$clog2(NPHYS)-1:0]    wr_addr,
    input  [63:0]                  wr_data,
    // read ports (2 per issue slot, dual-issue = 4 total)
    input  [$clog2(NPHYS)-1:0]    rd_addr0,
    input  [$clog2(NPHYS)-1:0]    rd_addr1,
    input  [$clog2(NPHYS)-1:0]    rd_addr2,
    input  [$clog2(NPHYS)-1:0]    rd_addr3,
    output [63:0]                  rd_data0,
    output [63:0]                  rd_data1,
    output [63:0]                  rd_data2,
    output [63:0]                  rd_data3
);

    reg [63:0] regs [0:NPHYS-1];

    // async read
    assign rd_data0 = regs[rd_addr0];
    assign rd_data1 = regs[rd_addr1];
    assign rd_data2 = regs[rd_addr2];
    assign rd_data3 = regs[rd_addr3];

    integer i;
    always @(posedge clk) begin
        if (reset) begin
            for (i = 0; i < NPHYS; i = i + 1)
                regs[i] <= 64'd0;
        end else if (wr_en) begin
            regs[wr_addr] <= wr_data;
        end
    end

endmodule


// ready bits — tracks which phys regs have valid data
// set when fu writes, clear on rename (in-flight)
module phys_reg_ready #(
    parameter NPHYS = 64
) (
    input                       clk,
    input                       reset,
    // clear on rename (new in-flight dest)
    input                       clear_en,
    input [$clog2(NPHYS)-1:0]  clear_addr,
    // set on cdb broadcast
    input                       set_en,
    input [$clog2(NPHYS)-1:0]  set_addr,
    // query
    input [$clog2(NPHYS)-1:0]  q_addr0,
    input [$clog2(NPHYS)-1:0]  q_addr1,
    output                      q_ready0,
    output                      q_ready1
);

    reg ready [0:NPHYS-1];

    assign q_ready0 = ready[q_addr0];
    assign q_ready1 = ready[q_addr1];

    integer i;
    always @(posedge clk) begin
        if (reset) begin
            for (i = 0; i < NPHYS; i = i + 1)
                ready[i] <= 1'b1; // all phys regs ready at reset
        end else begin
            if (clear_en) ready[clear_addr] <= 1'b0;
            if (set_en)   ready[set_addr]   <= 1'b1;
        end
    end

endmodule

// rat.sv — register alias table (rename stage)
// maps 32 arch regs -> 64 phys regs
// free list tracks available phys regs
// dual-issue: renames 2 instrs per cycle

module rat #(
    parameter NARCH  = 32,
    parameter NPHYS  = 64,
    parameter ARCH_W = 5,
    parameter PHYS_W = 6
) (
    input          clk,
    input          reset,

    // --- rename port 0 (instr 0 of dual-issue pair) ---
    input          rename0_en,
    input [ARCH_W-1:0] arch_rs0,   // src a arch reg
    input [ARCH_W-1:0] arch_rt0,   // src b arch reg
    input [ARCH_W-1:0] arch_rd0,   // dest arch reg
    input              has_dest0,  // instr writes a reg
    output [PHYS_W-1:0] phys_rs0,  // renamed src a
    output [PHYS_W-1:0] phys_rt0,  // renamed src b
    output [PHYS_W-1:0] phys_rd0,  // new phys dest
    output [PHYS_W-1:0] phys_old_rd0, // prev mapping (for free on commit)
    output              alloc_ok0, // free list had a reg

    // --- rename port 1 (instr 1 of dual-issue pair) ---
    // note: port 1 sees port 0's write to map table
    input          rename1_en,
    input [ARCH_W-1:0] arch_rs1,
    input [ARCH_W-1:0] arch_rt1,
    input [ARCH_W-1:0] arch_rd1,
    input              has_dest1,
    output [PHYS_W-1:0] phys_rs1,
    output [PHYS_W-1:0] phys_rt1,
    output [PHYS_W-1:0] phys_rd1,
    output [PHYS_W-1:0] phys_old_rd1,
    output              alloc_ok1,

    // --- commit port (free old phys reg, unblock arch->phys) ---
    input          commit0_en,
    input [PHYS_W-1:0] commit0_free,   // old phys reg to free

    input          commit1_en,
    input [PHYS_W-1:0] commit1_free,

    // --- mispredict/flush: restore snapshot ---
    input          flush_en,
    input [PHYS_W-1:0] flush_map [0:NARCH-1]  // checkpoint map
);

    // map table: arch reg -> current phys reg
    reg [PHYS_W-1:0] map [0:NARCH-1];

    // free list — circular fifo of available phys regs
    // init: phys 32..63 are free (0..31 mirror arch regs)
    localparam FREE_DEPTH = NPHYS - NARCH; // 32 free initially
    reg [PHYS_W-1:0] free_list [0:NPHYS-1]; // generous sizing
    reg [5:0] free_head, free_tail;
    reg [6:0] free_count; // up to 64

    // combinational lookup of current mappings
    // port 0 reads map as-is
    assign phys_rs0     = map[arch_rs0];
    assign phys_rt0     = map[arch_rt0];
    assign phys_old_rd0 = map[arch_rd0];
    // next free phys for port 0 dest
    assign phys_rd0     = (has_dest0 && alloc_ok0) ? free_list[free_head] : map[arch_rd0];
    assign alloc_ok0    = (free_count >= 1);

    // port 1 sees port 0's tentative update
    // if port 0 wrote arch_rd0 -> phys_rd0, port 1 must see that
    wire [PHYS_W-1:0] map1_rs1 = (rename0_en && has_dest0 && (arch_rd0 == arch_rs1)) 
                                  ? phys_rd0 : map[arch_rs1];
    wire [PHYS_W-1:0] map1_rt1 = (rename0_en && has_dest0 && (arch_rd0 == arch_rt1)) 
                                  ? phys_rd0 : map[arch_rt1];
    wire [PHYS_W-1:0] map1_old_rd1 = (rename0_en && has_dest0 && (arch_rd0 == arch_rd1))
                                  ? phys_rd0 : map[arch_rd1];

    assign phys_rs1     = map1_rs1;
    assign phys_rt1     = map1_rt1;
    assign phys_old_rd1 = map1_old_rd1;
    // port 1 needs second free reg (head+1 if port 0 also allocated)
    wire [5:0] free_head1 = (rename0_en && has_dest0 && alloc_ok0) 
                             ? (free_head + 1) : free_head;
    assign phys_rd1     = (has_dest1 && alloc_ok1) ? free_list[free_head1] : map1_old_rd1;
    assign alloc_ok1    = (has_dest1) ? (free_count >= (has_dest0 ? 2 : 1)) : 1'b1;

    integer i;
    always @(posedge clk) begin
        if (reset) begin
            // arch reg i maps to phys reg i (identity)
            for (i = 0; i < NARCH; i = i + 1)
                map[i] <= i; // Verilog automatically truncates 'i' to PHYS_W bits
            
            // free list: phys 32..63
            for (i = 0; i < FREE_DEPTH; i = i + 1)
                free_list[i] <= NARCH + i; // Logic fixed: no manual slicing needed
                
            free_head  <= 6'd0;
            free_tail  <= FREE_DEPTH[5:0];
            free_count <= FREE_DEPTH[6:0];

        end else if (flush_en) begin
            // restore checkpoint map on mispredict
            for (i = 0; i < NARCH; i = i + 1)
                map[i] <= flush_map[i];
            // note: free list recovery needs rob to return freed phys regs
            // simplified: trust that committed free regs are re-enqueued

        end else begin
            // commit frees — push old phys regs back
            if (commit0_en) begin
                free_list[free_tail] <= commit0_free;
                free_tail  <= free_tail + 1;
                free_count <= free_count + 1;
            end
            if (commit1_en) begin
                free_list[commit1_en ? (free_tail + commit0_en) : free_tail] <= commit1_free;
                free_tail  <= free_tail + 1 + commit0_en;
                free_count <= free_count + 1 + commit0_en;
            end

            // rename port 0
            if (rename0_en && has_dest0 && alloc_ok0) begin
                map[arch_rd0] <= free_list[free_head];
                free_head     <= free_head + 1;
                free_count    <= free_count - 1;
            end

            // rename port 1 (sees port 0's map update via combinational above)
            if (rename1_en && has_dest1 && alloc_ok1) begin
                map[arch_rd1] <= free_list[free_head1];
                free_head     <= free_head1 + 1;
                free_count    <= free_count - (has_dest0 && rename0_en ? 2 : 1);
            end
        end
    end

endmodule

test/regfile_tb.sv
// tb_regfile.sv — unit tests for reg_file module
module tb_regfile;

  reg clk, reset, write;
  reg [4:0] raddr1, raddr2, raddr3, waddr;
  reg [63:0] data;
  wire [63:0] r1, r2, r3;

  reg_file dut (
      .clk   (clk),
      .reset (reset),
      .raddr1(raddr1),
      .raddr2(raddr2),
      .raddr3(raddr3),
      .waddr (waddr),
      .data  (data),
      .write (write),
      .r1    (r1),
      .r2    (r2),
      .r3    (r3)
  );

  always #5 clk = ~clk;

  integer pass_count, fail_count, i;

  task check64;
    input [63:0] expected, got;
    input [255:0] name;
    begin
      if (got === expected) begin
        $display("  pass [%s]: 0x%016h", name, got);
        pass_count = pass_count + 1;
      end else begin
        $display("  FAIL [%s]: got 0x%016h  exp 0x%016h", name, got, expected);
        fail_count = fail_count + 1;
      end
    end
  endtask

  task do_reset;
    begin
      reset = 1;
      write = 0;
      @(posedge clk);
      @(posedge clk);
      #1;
      reset = 0;
    end
  endtask

  task write_reg;
    input [4:0] reg_num;
    input [63:0] val;
    begin
      write = 1;
      waddr = reg_num;
      data  = val;
      @(posedge clk);
      #1;
      write = 0;
    end
  endtask

  initial begin
    $dumpfile("sim/tb_regfile.vcd");
    $dumpvars(0, tb_regfile);
    clk = 0;
    pass_count = 0;
    fail_count = 0;
    raddr1 = 0;
    raddr2 = 0;
    raddr3 = 0;
    do_reset();

    // reset: r0-r30=0, r31=stack ptr (512*1024=524288)
    $display("\n--- reset state ---");
    begin
      integer all_zero;
      all_zero = 1;
      for (i = 0; i < 31; i = i + 1) begin
        raddr1 = i;
        #1;
        if (r1 !== 64'd0) all_zero = 0;
      end
      if (all_zero) begin
        $display("  pass [r0-r30_zero]");
        pass_count = pass_count + 1;
      end else begin
        $display("  FAIL [r0-r30_zero]");
        fail_count = fail_count + 1;
      end
    end
    raddr1 = 5'd31;
    #1;
    check64(64'd524288, r1, "reset_r31");

    // basic write/read via r1
    $display("\n--- read/write ---");
    write_reg(5'd1, 64'hDEADBEEFCAFEBABE);
    raddr1 = 5'd1;
    #1;
    check64(64'hDEADBEEFCAFEBABE, r1, "wr_r1");

    write_reg(5'd15, 64'd12345);
    raddr1 = 5'd15;
    #1;
    check64(64'd12345, r1, "wr_r15");

    // simultaneous two-port read r1+r2
    write_reg(5'd2, 64'd100);
    write_reg(5'd3, 64'd200);
    raddr1 = 5'd2;
    raddr2 = 5'd3;
    #1;
    check64(64'd100, r1, "2port_r2");
    check64(64'd200, r2, "2port_r3");

    // third port r3 via raddr3 (brgt rt)
    write_reg(5'd7, 64'd777);
    raddr3 = 5'd7;
    #1;
    check64(64'd777, r3, "3port_r7");

    // overwrite
    write_reg(5'd1, 64'd999);
    raddr1 = 5'd1;
    #1;
    check64(64'd999, r1, "overwrite_r1");

    // r31 writable (call/return update stack ptr)
    write_reg(5'd31, 64'd0);
    raddr1 = 5'd31;
    #1;
    check64(64'd0, r1, "wr_r31");

    // write=0 gates write
    $display("\n--- write gating ---");
    write_reg(5'd5, 64'd42);
    write = 0;
    waddr = 5'd5;
    data  = 64'd999;
    @(posedge clk);
    #1;
    raddr1 = 5'd5;
    #1;
    check64(64'd42, r1, "write_gated");

    // re-reset
    $display("\n--- re-reset ---");
    write_reg(5'd8, 64'hFFFFFFFFFFFFFFFF);
    do_reset();
    raddr1 = 5'd8;
    #1;
    check64(64'd0, r1, "rereset_r8");
    raddr1 = 5'd31;
    #1;
    check64(64'd524288, r1, "rereset_r31");

    $display("\n--- results: %0d passed, %0d failed ---", pass_count, fail_count);
    $finish;
  end
endmodule

sim/tb_regfile.vcd
$date
	Mon Apr 13 16:30:26 2026
$end
$version
	Icarus Verilog
$end
$timescale
	1s
$end
$scope module tb_regfile $end
$var wire 64 ! r3 [63:0] $end
$var wire 64 " r2 [63:0] $end
$var wire 64 # r1 [63:0] $end
$var reg 1 $ clk $end
$var reg 64 % data [63:0] $end
$var reg 5 & raddr1 [4:0] $end
$var reg 5 ' raddr2 [4:0] $end
$var reg 5 ( raddr3 [4:0] $end
$var reg 1 ) reset $end
$var reg 5 * waddr [4:0] $end
$var reg 1 + write $end
$var integer 32 , fail_count [31:0] $end
$var integer 32 - i [31:0] $end
$var integer 32 . pass_count [31:0] $end
$scope module dut $end
$var wire 1 $ clk $end
$var wire 64 / data [63:0] $end
$var wire 64 0 r1 [63:0] $end
$var wire 64 1 r2 [63:0] $end
$var wire 64 2 r3 [63:0] $end
$var wire 5 3 raddr1 [4:0] $end
$var wire 5 4 raddr2 [4:0] $end
$var wire 5 5 raddr3 [4:0] $end
$var wire 1 ) reset $end
$var wire 5 6 waddr [4:0] $end
$var wire 1 + write $end
$var integer 32 7 i [31:0] $end
$upscope $end
$scope begin $unm_blk_7 $end
$var integer 32 8 all_zero [31:0] $end
$upscope $end
$scope task check64 $end
$var reg 64 9 expected [63:0] $end
$var reg 64 : got [63:0] $end
$var reg 256 ; name [255:0] $end
$upscope $end
$scope task do_reset $end
$upscope $end
$scope task write_reg $end
$var reg 5 < reg_num [4:0] $end
$var reg 64 = val [63:0] $end
$upscope $end
$upscope $end
$enddefinitions $end
$comment Show the parameter values. $end
$dumpall
$end
#0
$dumpvars
bx =
bx <
bx ;
bx :
bx 9
bx 8
bx 7
bx 6
b0 5
b0 4
b0 3
bx 2
bx 1
bx 0
bx /
b0 .
bx -
b0 ,
0+
bx *
1)
b0 (
b0 '
b0 &
bx %
0$
bx #
bx "
bx !
$end
#5
b0 #
b0 0
b0 "
b0 1
b0 !
b0 2
b11111 7
1$
#10
0$
#15
b11111 7
1$
#16
b0 -
b1 8
0)
#17
b1 &
b1 3
b1 -
#18
b10 &
b10 3
b10 -
#19
b11 &
b11 3
b11 -
#20
b100 &
b100 3
b100 -
0$
#21
b101 &
b101 3
b101 -
#22
b110 &
b110 3
b110 -
#23
b111 &
b111 3
b111 -
#24
b1000 &
b1000 3
b1000 -
#25
b1001 &
b1001 3
b1001 -
1$
#26
b1010 &
b1010 3
b1010 -
#27
b1011 &
b1011 3
b1011 -
#28
b1100 &
b1100 3
b1100 -
#29
b1101 &
b1101 3
b1101 -
#30
b1110 &
b1110 3
b1110 -
0$
#31
b1111 &
b1111 3
b1111 -
#32
b10000 &
b10000 3
b10000 -
#33
b10001 &
b10001 3
b10001 -
#34
b10010 &
b10010 3
b10010 -
#35
b10011 &
b10011 3
b10011 -
1$
#36
b10100 &
b10100 3
b10100 -
#37
b10101 &
b10101 3
b10101 -
#38
b10110 &
b10110 3
b10110 -
#39
b10111 &
b10111 3
b10111 -
#40
b11000 &
b11000 3
b11000 -
0$
#41
b11001 &
b11001 3
b11001 -
#42
b11010 &
b11010 3
b11010 -
#43
b11011 &
b11011 3
b11011 -
#44
b11100 &
b11100 3
b11100 -
#45
b11101 &
b11101 3
b11101 -
1$
#46
b11110 &
b11110 3
b11110 -
#47
b10000000000000000000 #
b10000000000000000000 0
b11111 &
b11111 3
b1 .
b11111 -
#48
b1101111010101101101111101110111111001010111111101011101010111110 %
b1101111010101101101111101110111111001010111111101011101010111110 /
b1 *
b1 6
1+
b1101111010101101101111101110111111001010111111101011101010111110 =
b1 <
b10 .
b11100100110010101110011011001010111010001011111011100100011001100110001 ;
b10000000000000000000 :
b10000000000000000000 9
#50
0$
#55
1$
#56
b1101111010101101101111101110111111001010111111101011101010111110 #
b1101111010101101101111101110111111001010111111101011101010111110 0
b1 &
b1 3
0+
#57
b11000000111001 %
b11000000111001 /
b1111 *
b1111 6
1+
b11000000111001 =
b1111 <
b11 .
b111011101110010010111110111001000110001 ;
b1101111010101101101111101110111111001010111111101011101010111110 :
b1101111010101101101111101110111111001010111111101011101010111110 9
#60
0$
#65
1$
#66
b11000000111001 #
b11000000111001 0
b1111 &
b1111 3
0+
#67
b1100100 %
b1100100 /
b10 *
b10 6
1+
b1100100 =
b10 <
b100 .
b11101110111001001011111011100100011000100110101 ;
b11000000111001 :
b11000000111001 9
#70
0$
#75
1$
#76
b11001000 %
b11001000 /
b11 *
b11 6
b11001000 =
b11 <
1+
#80
0$
#85
1$
#86
b11001000 "
b11001000 1
b11 '
b11 4
b1100100 #
b1100100 0
b10 &
b10 3
0+
#87
b1100001001 %
b1100001001 /
b111 *
b111 6
1+
b1100001001 =
b111 <
b110 .
b11001001110000011011110111001001110100010111110111001000110011 ;
b11001000 :
b11001000 9
#90
0$
#95
1$
#96
b1100001001 !
b1100001001 2
b111 (
b111 5
0+
#97
b1111100111 %
b1111100111 /
b1 *
b1 6
1+
b1111100111 =
b1 <
b111 .
b11001101110000011011110111001001110100010111110111001000110111 ;
b1100001001 :
b1100001001 9
#100
0$
#105
1$
#106
b1111100111 #
b1111100111 0
b1 &
b1 3
0+
#107
b0 %
b0 /
b11111 *
b11111 6
1+
b0 =
b11111 <
b1000 .
b11011110111011001100101011100100111011101110010011010010111010001100101010111110111001000110001 ;
b1111100111 :
b1111100111 9
#110
0$
#115
1$
#116
b0 #
b0 0
b11111 &
b11111 3
0+
#117
b101010 %
b101010 /
b101 *
b101 6
1+
b101010 =
b101 <
b1001 .
b11101110111001001011111011100100011001100110001 ;
b0 :
b0 9
#120
0$
#125
1$
#126
b1111100111 %
b1111100111 /
0+
#130
0$
#135
1$
#136
b101010 #
b101010 0
b101 &
b101 3
#137
b1111111111111111111111111111111111111111111111111111111111111111 %
b1111111111111111111111111111111111111111111111111111111111111111 /
b1000 *
b1000 6
1+
b1111111111111111111111111111111111111111111111111111111111111111 =
b1000 <
b1010 .
b111011101110010011010010111010001100101010111110110011101100001011101000110010101100100 ;
b101010 :
b101010 9
#140
0$
#145
1$
#146
1)
0+
#150
0$
#155
b0 !
b0 2
b0 #
b0 0
b0 "
b0 1
b11111 7
1$
#160
0$
#165
b11111 7
1$
#166
b1000 &
b1000 3
0)
#167
b10000000000000000000 #
b10000000000000000000 0
b11111 &
b11111 3
b1011 .
b1110010011001010111001001100101011100110110010101110100010111110111001000111000 ;
b0 :
b0 9
#168
b1100 .
b111001001100101011100100110010101110011011001010111010001011111011100100011001100110001 ;
b10000000000000000000 :
b10000000000000000000 9
